{
  "workflow_name": "example-workflow",
  "workflow_version": "1.0.0",
  "workflow_file": "",
  "status": "running",
  "cursor": 0,
  "started_at": "2026-04-04T08:47:43.000Z",
  "updated_at": "2026-04-04T08:47:43.000Z",
  "steps": [
    {
      "id": "check-env",
      "type": "command",
      "status": "pending",
      "started_at": null,
      "completed_at": null,
      "output": null,
      "command_log": [],
      "agents": {},
      "loop_iteration": 0
    },
    {
      "id": "generate-report",
      "type": "agent",
      "status": "pending",
      "started_at": null,
      "completed_at": null,
      "output": null,
      "command_log": [],
      "agents": {},
      "loop_iteration": 0
    },
    {
      "id": "verify-report",
      "type": "command",
      "status": "pending",
      "started_at": null,
      "completed_at": null,
      "output": null,
      "command_log": [],
      "agents": {},
      "loop_iteration": 0
    }
  ]
}
